spaceone/__init__.py
spaceone/config/__init__.py
spaceone/config/api/__init__.py
spaceone/config/api/v1/__init__.py
spaceone/config/api/v1/domain_config.py
spaceone/config/api/v1/user_config.py
spaceone/config/conf/__init__.py
spaceone/config/conf/global_conf.py
spaceone/config/conf/proto_conf.py
spaceone/config/connector/__init__.py
spaceone/config/error/__init__.py
spaceone/config/info/__init__.py
spaceone/config/info/common_info.py
spaceone/config/info/domain_config_info.py
spaceone/config/info/user_config_info.py
spaceone/config/lib/__init__.py
spaceone/config/manager/__init__.py
spaceone/config/manager/domain_config_manager.py
spaceone/config/manager/user_config_manager.py
spaceone/config/model/__init__.py
spaceone/config/model/domain_config_model.py
spaceone/config/model/user_config_model.py
spaceone/config/service/__init__.py
spaceone/config/service/domain_config_service.py
spaceone/config/service/user_config_service.py
spaceone_config_test_PyPI_2FA-1.0.0.dist-info/METADATA
spaceone_config_test_PyPI_2FA-1.0.0.dist-info/WHEEL
spaceone_config_test_PyPI_2FA-1.0.0.dist-info/top_level.txt
spaceone_config_test_PyPI_2FA-1.0.0.dist-info/RECORD
