Metadata-Version: 2.1
Name: spaceone-config-test-PyPI-2FA
Version: 1.0.0
Summary: SpaceONE config service PyPI test
Home-page: UNKNOWN
Author: MEGAZONE SpaceONE Team
Author-email: pyt4105@gmail.com
License: Apache License 2.0
Platform: UNKNOWN
